ubit_kernel/__init__.py
ubit_kernel/__main__.py
ubit_kernel/install.py
ubit_kernel/kernel.py
ubit_kernel/ubit.py
ubit_kernel-0.3.dist-info/WHEEL
ubit_kernel-0.3.dist-info/METADATA
ubit_kernel-0.3.dist-info/RECORD
