Metadata-Version: 1.2
Name: ubit_kernel
Version: 0.3
Summary: A Jupyter kernel for MicroPython on the BBC micro:bit
Home-page: https://github.com/takluyver/ubit_kernel
License: UNKNOWN
Author: Thomas Kluyver
Author-email: thomas@kluyver.me.uk
Requires-Python: >=3
Classifier: License :: OSI Approved :: MIT License
Classifier: Framework :: IPython
Classifier: Intended Audience :: Developers
Classifier: Intended Audience :: Education
Classifier: Programming Language :: Python :: 3
Classifier: Topic :: Education
Classifier: Topic :: Software Development :: Embedded Systems
Requires-Dist: pyserial
Requires-Dist: ipykernel
